[
  {
  "id": 13,
  "title": "SearchTap vs. Searchanise",
  "date": "07th Dec 2018",
  "url": "searchtap-vs-searchanise/",
  "image": "searchtap-vs-searchanise.jpg",
  "about": "Shopify has enabled many entrepreneurs to take the first steps in their e-commerce journey. With setting up a store..."
},
  {
    "id": 12,
    "title": "22 ways to increase conversions",
    "date": "03rd Dec 2018",
    "url": "22-ways-to-increase-conversions/",
    "image": "increase-conversions.jpg",
    "about": "You are no doubt thinking about how to increase your e-commerce stores conversion rates a lot of the times..."
  },
  {
    "id": 11,
    "title": "Is Shopify's search costing you sales",
    "date": "27th Nov 2018",
    "url": "pre-and-post-implementation-shopify/",
    "image": "shopify-implementation.jpg",
    "about": "Shopify has enabled many entrepreneurs to take the first steps..."
  },
  {
    "id": 10,
    "title": "How can you improve your Magento 1.x search",
    "date": "19th Nov 2018",
    "url": "pre-and-post-implementation-magento-1/",
    "image": "implementation-magento-1.jpg",
    "about": "Search is a critical feature for any e-commerce store. It helps visitors cut through..."
  },
  {
    "id": 9,
    "title": "Improve conversions with search analytics",
    "date": "16th Nov 2018",
    "url": "improve-conversions-with-search-analytics/",
    "image": "search-analytics.jpg",
    "about": "Using search is the first interaction that 25% of visitors make on an e-commerce website..."
  },
  {
    "id": 8,
    "title": "Get higher conversions with a competent site search",
    "date": "14th Nov 2018",
    "url": "get-higher-conversions-with-a-competent-site-search/",
    "image": "higher-conversions-with-site-search.jpg",
    "about": "One of the most ignored segments of an e-commerce site is their search users. These shoppers are generally at the..."
  },
  {
    "id": 7,
    "title": "Ignoring e-commerce search can cost you sales",
    "date": "09th Nov 2018",
    "url": "ignoring-e-commerce-search-can-cost-you-sales/",
    "image": "search-can-cost-you-sales.jpg",
    "about": "15 seconds is all the time that an e-commerce business has to successfully engage a visitor. All the time energy and effort spent on your..."
  },
  {
    "id": 6,
    "title": "10 tips on dealing with Zero Search Results",
    "date": "06th Nov 2018",
    "url": "10-tips-on-dealing-with-zero-search-results/",
    "image": "zero-search-results.jpg",
    "about": "Nothing is more frustrating for a visitor to when their browsing experience..."
  },
  {
    "id": 5,
    "title": "Get better results with Magento 2.x search",
    "date": "04th Nov 2018",
    "url": "pre-and-post-implementation-magento-2/",
    "image": "implementation-magento-2.jpg",
    "about": "Search users have contributed up to 30% of revenues to an e-commerce business. Your platform needs..."
  },
  {
    "id": 4,
    "title": "10 tips for a better mobile search UX",
    "date": "01st Nov 2018",
    "url": "10-tips-for-a-better-mobile-search-ux/",
    "image": "mobile-search-UX.jpg",
    "about": "With the growth in the mobile sphere e-commerce businesses have shifted their focus to serving this sort..."
  },
  {
    "id": 3,
    "title": "5 Reasons to track revenue with enhanced e-commerce tracking",
    "date": "31st Oct 2018",
    "url": "5-reasons-to-track-revenue-with-enhanced-e-commerce-tracking/",
    "image": "track-revenue-enhanced-e-com.jpg",
    "about": "Google Analytics’ goal tracking itself is an important metric. That is not under contention..."
  },
  {
    "id": 2,
    "title": "Personalization Isn’t Improving Your Customer Engagement- Here’s Why",
    "date": "27th Oct 2018",
    "url": "personalization-is-not-improving-your-customer-engagement/",
    "image": "customer-engagement.jpg",
    "about": "A big misstep small e-commerce companies make is thinking that personalization can help them achieve more conversions..."
  },
  {
    "id": 1,
    "title": "Evolution of search as you type",
    "date": "27th Oct 2018",
    "url": "evolution-of-search-as-you-type/",
    "image": "evolution-of-search-as-you-type.jpg",
    "about": "E-commerce search users don’t just want to see results for their search queries..."
  }
]